{"otherData": {}, "displayTimeUnit": "ms", "traceEvents": [{"name": "ym::Config::load","cat": "function","ph": "X","pid": 0,"tid": 0,"ts": 105848919866,"dur": 59},{"name": "ym::Config::load","cat": "function","ph": "X","pid": 0,"tid": 0,"ts": 105848920159,"dur": 125},{"name": "ym::Config::load","cat": "function","ph": "X","pid": 0,"tid": 0,"ts": 105848920342,"dur": 49},{"name": "ym::Config::load","cat": "function","ph": "X","pid": 0,"tid": 0,"ts": 105848919834,"dur": 602},{"name": "ym::Config::readFile","cat": "function","ph": "X","pid": 0,"tid": 0,"ts": 105848917142,"dur": 3495},{"name": "ym::Config::init","cat": "function","ph": "X","pid": 0,"tid": 0,"ts": 105848917138,"dur": 3551},{"name": "ym::DisplayDesc::init","cat": "function","ph": "X","pid": 0,"tid": 0,"ts": 105848923171,"dur": 53},{"name": "ym::Display::init","cat": "function","ph": "X","pid": 0,"tid": 0,"ts": 105849166901,"dur": 20899},{"name": "ym::Input::init","cat": "function","ph": "X","pid": 0,"tid": 0,"ts": 105849187906,"dur": 2593},{"name": "ym::App::App","cat": "function","ph": "X","pid": 0,"tid": 0,"ts": 105848916251,"dur": 536905},{"name": "ym::LayerManager::push","cat": "function","ph": "X","pid": 0,"tid": 0,"ts": 105849453489,"dur": 5}]
}